motionstracker/__init__.py
motionstracker/__main__.py
motionstracker/utils/Class.py
motionstracker/utils/__init__.py
motionstracker/utils/functions.py
motionstracker/utils/variables.py
motionstracker-2.2.1.dist-info/LICENSE
motionstracker-2.2.1.dist-info/METADATA
motionstracker-2.2.1.dist-info/WHEEL
motionstracker-2.2.1.dist-info/top_level.txt
motionstracker-2.2.1.dist-info/RECORD
