Metadata-Version: 2.1
Name: motionstracker
Version: 2.2.1
Summary: A module that allows you to Track the movements of webcam images and save them as images or as a single video.
Home-page: https://github.com/Ridoineel/motions-tracker
Author: RidoineEl
Author-email: ridoineelofficiel@gmail.com
Project-URL: Bug Tracker, https://github.com/Ridoineel/motions-tracker/log-module/issues
Classifier: Programming Language :: Python :: 3
Classifier: License :: OSI Approved :: MIT License
Classifier: Operating System :: OS Independent
Requires-Python: >=3.6
License-File: LICENSE
Requires-Dist: opencv-python
Requires-Dist: numpy
Requires-Dist: scipy
Requires-Dist: matplotlib
Requires-Dist: pillow
